vidgear_noperm/__init__.py
vidgear_noperm/version.py
vidgear_noperm/gears/__init__.py
vidgear_noperm/gears/camgear.py
vidgear_noperm/gears/helper.py
vidgear_noperm/gears/netgear.py
vidgear_noperm/gears/pigear.py
vidgear_noperm/gears/screengear.py
vidgear_noperm/gears/stabilizer.py
vidgear_noperm/gears/streamgear.py
vidgear_noperm/gears/videogear.py
vidgear_noperm/gears/writegear.py
vidgear_noperm/gears/asyncio/__init__.py
vidgear_noperm/gears/asyncio/__main__.py
vidgear_noperm/gears/asyncio/helper.py
vidgear_noperm/gears/asyncio/netgear_async.py
vidgear_noperm/gears/asyncio/webgear.py
vidgear_noperm/gears/asyncio/webgear_rtc.py
vidgear_noperm-1.3.dist-info/LICENSE
vidgear_noperm-1.3.dist-info/METADATA
vidgear_noperm-1.3.dist-info/WHEEL
vidgear_noperm-1.3.dist-info/top_level.txt
vidgear_noperm-1.3.dist-info/RECORD
