Metadata-Version: 2.1
Name: vidgear-noperm
Version: 1.3
Summary: A modified variation of abhiTronix's vidgear. In this variation, it is possible to write the output file anywhere regardless the permissions.
Home-page: https://github.com/egeakman/vidgear_noperm
Author: Ege Akman
Author-email: egeakmanegeakman@hotmail.com
License: Apache License 2.0
Project-URL: Issues, https://github.com/abhiTronix/vidgear/issues
Project-URL: Forked From, https://github.com/abhiTronix/vidgear
Project-URL: Documentation, https://abhitronix.github.io/vidgear
Project-URL: Ege Akman's GitHub Profile, https://github.com/egeakman
Keywords: OpenCV,vidgear,write,anywhere,no,permission,multithreading,FFmpeg,picamera,starlette,mss,pyzmq,aiortc,uvicorn,uvloop,pafy,youtube-dl,asyncio,dash,streamlink,Video Processing,Video Stablization,Computer Vision,Video Streaming,raspberrypi,YouTube,Twitch,WebRTC
Platform: UNKNOWN
Classifier: Development Status :: 5 - Production/Stable
Classifier: Operating System :: POSIX
Classifier: Operating System :: MacOS :: MacOS X
Classifier: Operating System :: Microsoft :: Windows
Classifier: Topic :: Multimedia :: Video
Classifier: Topic :: Scientific/Engineering
Classifier: Intended Audience :: Developers
Classifier: Intended Audience :: Science/Research
Classifier: Intended Audience :: Education
Classifier: License :: OSI Approved :: Apache Software License
Classifier: Programming Language :: Python :: 3.6
Classifier: Programming Language :: Python :: 3.7
Classifier: Programming Language :: Python :: 3.8
Classifier: Programming Language :: Python :: 3.9
Requires-Python: >=3.6
License-File: LICENSE
Requires-Dist: pafy (>=0.5.5)
Requires-Dist: mss (>=6.1.0)
Requires-Dist: numpy
Requires-Dist: youtube-dl (>=2021.6.6)
Requires-Dist: streamlink (>=2.2.0)
Requires-Dist: requests (>=2.9.2)
Requires-Dist: pyzmq (>=22.1.0)
Requires-Dist: simplejpeg
Requires-Dist: colorlog
Requires-Dist: colorama
Requires-Dist: tqdm
Requires-Dist: Pillow
Requires-Dist: pyscreenshot (>=3.0)
Provides-Extra: asyncio
Requires-Dist: starlette (>=0.9.9) ; extra == 'asyncio'
Requires-Dist: aiofiles ; extra == 'asyncio'
Requires-Dist: jinja2 ; extra == 'asyncio'
Requires-Dist: aiohttp ; extra == 'asyncio'
Requires-Dist: uvicorn (>=0.9.1) ; extra == 'asyncio'
Requires-Dist: msgpack-numpy ; extra == 'asyncio'
